wattson/__init__.py
wattson/consts.py
wattson/data.py
wattson/estimator.py
wattson/interpolation.py
wattson/test_estimator.py
wattson/test_interpolation.py
wattson/types.py
valohai_wattson-22.5.0.dist-info/LICENSE
valohai_wattson-22.5.0.dist-info/METADATA
valohai_wattson-22.5.0.dist-info/WHEEL
valohai_wattson-22.5.0.dist-info/top_level.txt
valohai_wattson-22.5.0.dist-info/RECORD
