Metadata-Version: 2.1
Name: valohai-wattson
Version: 22.5.0
Summary: Carbon emissions calculator
Home-page: https://github.com/valohai/wattson
Author: Valohai
Author-email: info@valohai.com
License: MIT
Requires-Python: >=3.7
License-File: LICENSE
Provides-Extra: dev
Requires-Dist: black ; extra == 'dev'
Requires-Dist: flake8 ; extra == 'dev'
Requires-Dist: flake8-isort ; extra == 'dev'
Requires-Dist: isort ; extra == 'dev'
Requires-Dist: mypy ; extra == 'dev'
Requires-Dist: pytest ; extra == 'dev'
Provides-Extra: test
Requires-Dist: black ; extra == 'test'
Requires-Dist: pytest ; extra == 'test'
Requires-Dist: pytest-cov ; extra == 'test'
